{"archive":true,"raw":true,"resources":true,"archive\\base":true,"archive\\base\\localization":true,"customSounds":true,"raw\\base":true,"raw\\base\\localization":true,"raw\\base\\localization\\en-us":true,"raw\\base\\localization\\en-us\\onscreens":true,"resources\\archive":true,"resources\\archive\\pc":true,"resources\\archive\\pc\\mod":true,"resources\\r6":true,"resources\\r6\\scripts":true,"resources\\r6\\scripts\\No RNG Bonus":true,"resources\\r6\\tweaks":true,"resources\\r6\\tweaks\\No RNG Bonus":true}